stcal/dqflags.py
stcal/conftest.py
stcal/_version.py
stcal/velocity_aberration.py
stcal/basic_utils.py
stcal/__init__.py
stcal/testing_helpers.py
stcal/dynamicdq.py
stcal/resample/resample.py
stcal/resample/__init__.py
stcal/resample/utils.py
stcal/skymatch/__init__.py
stcal/skymatch/skystatistics.py
stcal/skymatch/skymatch.py
stcal/skymatch/skyimage.py
stcal/jump/twopoint_difference.py
stcal/jump/jump.py
stcal/jump/__init__.py
stcal/jump/twopoint_difference_class.py
stcal/jump/jump_class.py
stcal/ramp_fitting/ols_fit.py
stcal/ramp_fitting/likely_fit.py
stcal/ramp_fitting/slope_fitter.cpython-311-darwin.so
stcal/ramp_fitting/__init__.py
stcal/ramp_fitting/ramp_fit.py
stcal/ramp_fitting/ramp_fit_class.py
stcal/ramp_fitting/utils.py
stcal/ramp_fitting/ols_cas22_fit.py
stcal/ramp_fitting/likely_algo_classes.py
stcal/ramp_fitting/ols_cas22/_ramp.pxd
stcal/ramp_fitting/ols_cas22/_ramp.cpp
stcal/ramp_fitting/ols_cas22/_fit.cpp
stcal/ramp_fitting/ols_cas22/_jump.pyx
stcal/ramp_fitting/ols_cas22/__init__.py
stcal/ramp_fitting/ols_cas22/_jump.cpython-311-darwin.so
stcal/ramp_fitting/ols_cas22/_jump.cpp
stcal/ramp_fitting/ols_cas22/_fit.pyx
stcal/ramp_fitting/ols_cas22/_jump.pxd
stcal/ramp_fitting/ols_cas22/_ramp.cpython-311-darwin.so
stcal/ramp_fitting/ols_cas22/_fit.cpython-311-darwin.so
stcal/ramp_fitting/ols_cas22/_ramp.pyx
stcal/ramp_fitting/src/slope_fitter.c
stcal/saturation/saturation.py
stcal/saturation/__init__.py
stcal/alignment/util.py
stcal/alignment/__init__.py
stcal/alignment/resample_utils.py
stcal/dark_current/dark_sub.py
stcal/dark_current/__init__.py
stcal/dark_current/dark_class.py
stcal/tweakreg/__init__.py
stcal/tweakreg/utils.py
stcal/tweakreg/astrometric_utils.py
stcal/tweakreg/tweakreg.py
stcal/outlier_detection/__init__.py
stcal/outlier_detection/utils.py
stcal/outlier_detection/median.py
stcal/linearity/linearity.py
stcal/linearity/__init__.py
stcal-1.15.2.dist-info/zip-safe
stcal-1.15.2.dist-info/RECORD
stcal-1.15.2.dist-info/WHEEL
stcal-1.15.2.dist-info/top_level.txt
stcal-1.15.2.dist-info/METADATA
stcal-1.15.2.dist-info/licenses/LICENSE
