Metadata-Version: 2.4
Name: stcal
Version: 1.15.2
Summary: STScI tools and algorithms used in calibration pipelines
Author-email: STScI <help@stsci.edu>
Project-URL: repository, https://github.com/spacetelescope/stcal
Project-URL: tracker, https://github.com/spacetelescope/stcal/issues
Classifier: Intended Audience :: Science/Research
Classifier: Topic :: Scientific/Engineering :: Astronomy
Classifier: Programming Language :: Python :: 3
Requires-Python: <3.14,>=3.11
License-File: LICENSE
Requires-Dist: astropy>=6.0.0
Requires-Dist: drizzle>=2.0.1
Requires-Dist: scipy>=1.14.1
Requires-Dist: scikit-image>=0.20.0
Requires-Dist: numpy>=1.25.0
Requires-Dist: opencv-python-headless>=4.6.0.66
Requires-Dist: asdf>=3.3.0
Requires-Dist: gwcs>=0.25.2
Requires-Dist: tweakwcs>=0.8.8
Requires-Dist: requests>=2.22
Requires-Dist: spherical-geometry>=1.2.22
Provides-Extra: docs
Requires-Dist: numpydoc; extra == "docs"
Requires-Dist: packaging>=17; extra == "docs"
Requires-Dist: sphinx; extra == "docs"
Requires-Dist: sphinx-asdf; extra == "docs"
Requires-Dist: sphinx-astropy; extra == "docs"
Requires-Dist: sphinx-rtd-theme; extra == "docs"
Requires-Dist: tomli; python_version <= "3.11" and extra == "docs"
Provides-Extra: test
Requires-Dist: psutil; extra == "test"
Requires-Dist: pytest>=6; extra == "test"
Requires-Dist: pytest-cov; extra == "test"
Requires-Dist: pytest-doctestplus; extra == "test"
Dynamic: license-file
